twomartens.masterthesis-0.3.0-py3.8-nspkg.pth
twomartens/masterthesis/__init__.py
twomartens/masterthesis/cli.py
twomartens/masterthesis/config.py
twomartens/masterthesis/data.py
twomartens/masterthesis/definitions.py
twomartens/masterthesis/evaluate.py
twomartens/masterthesis/main.py
twomartens/masterthesis/plotting.py
twomartens/masterthesis/scenenet_pb2.py
twomartens/masterthesis/ssd.py
twomartens/masterthesis/weights.py
twomartens/masterthesis/ssd_keras/__init__.py
twomartens/masterthesis/ssd_keras/bounding_box_utils/__init__.py
twomartens/masterthesis/ssd_keras/bounding_box_utils/bounding_box_utils.py
twomartens/masterthesis/ssd_keras/data_generator/__init__.py
twomartens/masterthesis/ssd_keras/data_generator/data_augmentation_chain_constant_input_size.py
twomartens/masterthesis/ssd_keras/data_generator/data_augmentation_chain_original_ssd.py
twomartens/masterthesis/ssd_keras/data_generator/data_augmentation_chain_satellite.py
twomartens/masterthesis/ssd_keras/data_generator/data_augmentation_chain_variable_input_size.py
twomartens/masterthesis/ssd_keras/data_generator/object_detection_2d_data_generator.py
twomartens/masterthesis/ssd_keras/data_generator/object_detection_2d_geometric_ops.py
twomartens/masterthesis/ssd_keras/data_generator/object_detection_2d_image_boxes_validation_utils.py
twomartens/masterthesis/ssd_keras/data_generator/object_detection_2d_misc_utils.py
twomartens/masterthesis/ssd_keras/data_generator/object_detection_2d_patch_sampling_ops.py
twomartens/masterthesis/ssd_keras/data_generator/object_detection_2d_photometric_ops.py
twomartens/masterthesis/ssd_keras/eval_utils/__init__.py
twomartens/masterthesis/ssd_keras/eval_utils/average_precision_evaluator.py
twomartens/masterthesis/ssd_keras/eval_utils/coco_utils.py
twomartens/masterthesis/ssd_keras/keras_layers/__init__.py
twomartens/masterthesis/ssd_keras/keras_layers/keras_layer_AnchorBoxes.py
twomartens/masterthesis/ssd_keras/keras_layers/keras_layer_DecodeDetections.py
twomartens.masterthesis-0.3.0.dist-info/LICENSE
twomartens.masterthesis-0.3.0.dist-info/METADATA
twomartens.masterthesis-0.3.0.dist-info/WHEEL
twomartens.masterthesis-0.3.0.dist-info/entry_points.txt
twomartens.masterthesis-0.3.0.dist-info/namespace_packages.txt
twomartens.masterthesis-0.3.0.dist-info/top_level.txt
twomartens.masterthesis-0.3.0.dist-info/RECORD
