Metadata-Version: 2.1
Name: twomartens.masterthesis
Version: 0.3.0
Summary: Code of the master thesis
Home-page: https://git.2martens.de/2martens/masterthesis
Author: Jim Martens
Author-email: github@2martens.de
License: Apache License 2.0
Platform: UNKNOWN
Classifier: Operating System :: OS Independent
Classifier: Development Status :: 2 - Pre-Alpha
Classifier: License :: OSI Approved :: Apache Software License
Classifier: Environment :: Console
Classifier: Intended Audience :: Science/Research
Classifier: Topic :: Scientific/Engineering :: Artificial Intelligence
Classifier: Programming Language :: Python
Classifier: Programming Language :: Python :: 3
Classifier: Programming Language :: Python :: 3.6
Classifier: Programming Language :: Python :: 3.7
Classifier: Programming Language :: Python :: 3.8
Requires-Python: ~=3.6
Requires-Dist: tensorflow
Requires-Dist: Pillow
Requires-Dist: h5py
Requires-Dist: numpy
Requires-Dist: opencv-python
Requires-Dist: scikit-learn
Requires-Dist: tqdm
Requires-Dist: beautifulsoup4
Requires-Dist: matplotlib
Requires-Dist: protobuf
Requires-Dist: imutils
Requires-Dist: attributedict
Requires-Dist: cython
